bacpacs/__init__.py
bacpacs/bacpacs.py
bacpacs/cli.py
bacpacs/util.py
bacpacs-0.1.1.dist-info/METADATA
bacpacs-0.1.1.dist-info/RECORD
bacpacs-0.1.1.dist-info/WHEEL
bacpacs-0.1.1.dist-info/top_level.txt
