Metadata-Version: 2.1
Name: bacpacs
Version: 0.1.1
Summary: Bacterial Pathogenicity Classification via Sparse-SVM
Home-page: https://github.com/barashe/bacpacs
Author: Eran Barash
Author-email: barashe@post.bgu.ac.il
License: UNKNOWN
Platform: UNKNOWN
Classifier: Programming Language :: Python :: 2
Classifier: License :: OSI Approved :: MIT License
Classifier: Operating System :: POSIX :: Linux
Requires-Dist: numpy
Requires-Dist: pandas
Requires-Dist: scikit-learn
Requires-Dist: biopython
